{
  "cases" : [
    {
      "case_number" : "1",
      "surgery_type" : "Craniectomy",
      "surgeon" : "Jonathan Bresenham MD",
      "date" : "2016-12-01T19:31:38.514Z",
      "items" : [
        {
          "item_name" : "Safety IV Catheters - Radiopaque (Jelco)",
          "donating": "1",
          "total": "1",
          "cost": "135.00"
        },
        {
          "item_name" : "Shiley Tracheostomy Tube Cuffless with Disposable Inner Cannula (Covidian)",
          "donating": "2",
          "total": "3",
          "cost": "75.21"
        },
        {
          "item_name" : "Transpac IV Monitoring Kit (ICU Medical)",
          "donating": "3",
          "total": "4",
          "cost": "21.00"
        },
        {
          "item_name" : "0.9% Sodium Chloride Injection USP",
          "donating": "9",
          "total": "10",
          "cost": "10.95"
        },
        {
          "item_name" : "IV Secondary Set",
          "donating": "1",
          "total": "2",
          "cost": "5.00"
        }
      ]
    },
    {
      "case_number" : "2",
      "surgery_type" : "Ventriculo-Peritoneal Shunt",
      "surgeon" : "Young Lam MD",
      "date" : "2016-12-01T17:31:38.514Z",
      "items" : [
        {
          "item_name" : "Safety IV Catheters - Radiopaque (Jelco)",
          "donating": "1",
          "total": "1",
          "cost": "135.00"
        },
        {
          "item_name" : "Shiley Tracheostomy Tube Cuffless with Disposable Inner Cannula (Covidian)",
          "donating": "3",
          "total": "3",
          "cost": "75.21"
        },
        {
          "item_name" : "Dermacea USP Type VII Gauze (Covidien)",
          "donating": "0",
          "total": "10",
          "cost": "3.99"
        },
        {
          "item_name" : "0.9% Sodium Chloride Injection USP",
          "donating": "6",
          "total": "10",
          "cost": "10.95"
        },
        {
          "item_name" : "IV Secondary Set",
          "donating": "1",
          "total": "2",
          "cost": "5.00"
        }
      ]
    },
    {
      "case_number" : "3",
      "surgery_type" : "Craniectomy",
      "surgeon" : "Ethan Rutledge MD",
      "date" : "2016-12-01T19:31:38.514Z",
      "items" : [
        {
          "item_name" : "Safety IV Catheters - Radiopaque (Jelco)",
          "donating": "1",
          "total": "2",
          "cost": "135.00"
        },
        {
          "item_name" : "Shiley Tracheostomy Tube Cuffless with Disposable Inner Cannula (Covidian)",
          "donating": "0",
          "total": "3",
          "cost": "75.21"
        },
        {
          "item_name" : "Dermacea USP Type VII Gauze (Covidien)",
          "donating": "0",
          "total": "10",
          "cost": "3.99"
        },
        {
          "item_name" : "0.9% Sodium Chloride Injection USP",
          "donating": "1",
          "total": "5",
          "cost": "10.95"
        },
        {
          "item_name" : "IV Secondary Set",
          "donating": "1",
          "total": "2",
          "cost": "5.00"
        }
      ]
    },
    {
      "case_number" : "4",
      "surgery_type" : "Spinal Fusion",
      "surgeon" : "Jennifer Lasker MD, PhD",
      "date" : "2016-12-01T20:31:38.514Z",
      "items" : [
        {
          "item_name" : "Safety IV Catheters - Radiopaque (Jelco)",
          "donating": "2",
          "total": "3",
          "cost": "135.00"
        },
        {
          "item_name" : "Shiley Tracheostomy Tube Cuffless with Disposable Inner Cannula (Covidian)",
          "donating": "0",
          "total": "3",
          "cost": "75.21"
        },
        {
          "item_name" : "Dermacea USP Type VII Gauze (Covidien)",
          "donating": "3",
          "total": "20",
          "cost": "3.99"
        },
        {
          "item_name" : "0.9% Sodium Chloride Injection USP",
          "donating": "5",
          "total": "10",
          "cost": "10.95"
        },
        {
          "item_name" : "IV Secondary Set",
          "donating": "0",
          "total": "2",
          "cost": "5.00"
        }
      ]
    },
    {
      "case_number" : "5",
      "surgery_type" : "External Venticular Drain (EVD)",
      "surgeon" : "Michaela Sufid MD",
      "date" : "2016-12-02T21:31:38.514Z",
      "items" : [
        {
          "item_name" : "Safety IV Catheters - Radiopaque (Jelco)",
          "donating": "0",
          "total": "1",
          "cost": "135.00"
        },
        {
          "item_name" : "Shiley Tracheostomy Tube Cuffless with Disposable Inner Cannula (Covidian)",
          "donating": "2",
          "total": "3",
          "cost": "75.21"
        },
        {
          "item_name" : "Dermacea USP Type VII Gauze (Covidien)",
          "donating": "0",
          "total": "10",
          "cost": "3.99"
        },
        {
          "item_name" : "0.9% Sodium Chloride Injection USP",
          "donating": "9",
          "total": "11",
          "cost": "10.95"
        },
        {
          "item_name" : "IV Secondary Set",
          "donating": "2",
          "total": "2",
          "cost": "5.00"
        }
      ]
    },
    {
      "case_number" : "6",
      "surgery_type" : "Endoscopic Third Ventriculostomy (ETV)",
      "surgeon" : "Andrew Tran MD",
      "date" : "2016-12-02T21:49:38.514Z",
      "items" : [
        {
          "item_name" : "Safety IV Catheters - Radiopaque (Jelco)",
          "donating": "1",
          "total": "1",
          "cost": "135.00"
        },
        {
          "item_name" : "Shiley Tracheostomy Tube Cuffless with Disposable Inner Cannula (Covidian)",
          "donating": "3",
          "total": "3",
          "cost": "75.21"
        },
        {
          "item_name" : "Dermacea USP Type VII Gauze (Covidien)",
          "donating": "0",
          "total": "10",
          "cost": "3.99"
        },
        {
          "item_name" : "0.9% Sodium Chloride Injection USP",
          "donating": "8",
          "total": "10",
          "cost": "10.95"
        },
        {
          "item_name" : "IV Secondary Set",
          "donating": "0",
          "total": "2",
          "cost": "5.00"
        }
      ]
    },
    {
      "case_number" : "7",
      "surgery_type" : "Intrathecal Baclofen Pump",
      "surgeon" : "James Burke MD, PhD",
      "date" : "2016-12-02T22:01:38.514Z",
      "items" : [
        {
          "item_name" : "Safety IV Catheters - Radiopaque (Jelco)",
          "donating": "0",
          "total": "1",
          "cost": "135.00"
        },
        {
          "item_name" : "Shiley Tracheostomy Tube Cuffless with Disposable Inner Cannula (Covidian)",
          "donating": "0",
          "total": "3",
          "cost": "75.21"
        },
        {
          "item_name" : "Dermacea USP Type VII Gauze (Covidien)",
          "donating": "0",
          "total": "10",
          "cost": "3.99"
        },
        {
          "item_name" : "0.9% Sodium Chloride Injection USP",
          "donating": "8",
          "total": "10",
          "cost": "10.95"
        },
        {
          "item_name" : "IV Secondary Set",
          "donating": "2",
          "total": "2",
          "cost": "5.00"
        }
      ]
    },
    {
      "case_number" : "8",
      "surgery_type" : "Endoscopic Third Ventriculostomy (ETV)",
      "surgeon" : "Daniel Lau MD",
      "date" : "2016-12-02T22:10:38.514Z",
      "items" : [
        {
          "item_name" : "Safety IV Catheters - Radiopaque (Jelco)",
          "donating": "1",
          "total": "2",
          "cost": "135.00"
        },
        {
          "item_name" : "Shiley Tracheostomy Tube Cuffless with Disposable Inner Cannula (Covidian)",
          "donating": "0",
          "total": "3",
          "cost": "75.21"
        },
        {
          "item_name" : "Dermacea USP Type VII Gauze (Covidien)",
          "donating": "7",
          "total": "10",
          "cost": "3.99"
        },
        {
          "item_name" : "0.9% Sodium Chloride Injection USP",
          "donating": "4",
          "total": "10",
          "cost": "10.95"
        },
        {
          "item_name" : "IV Secondary Set",
          "donating": "0",
          "total": "2",
          "cost": "5.00"
        }
      ]
    },
    {
      "case_number" : "9",
      "surgery_type" : "Intrathecal Baclofen Pump",
      "surgeon" : "Corinna Georgiou MD",
      "date" : "2016-12-02T22:11:38.514Z",
      "items" : [
        {
          "item_name" : "Safety IV Catheters - Radiopaque (Jelco)",
          "donating": "0",
          "total": "1",
          "cost": "135.00"
        },
        {
          "item_name" : "Shiley Tracheostomy Tube Cuffless with Disposable Inner Cannula (Covidian)",
          "donating": "0",
          "total": "3",
          "cost": "75.21"
        },
        {
          "item_name" : "Dermacea USP Type VII Gauze (Covidien)",
          "donating": "0",
          "total": "10",
          "cost": "3.99"
        },
        {
          "item_name" : "0.9% Sodium Chloride Injection USP",
          "donating": "0",
          "total": "10",
          "cost": "10.95"
        },
        {
          "item_name" : "IV Secondary Set",
          "donating": "0",
          "total": "2",
          "cost": "5.00"
        }
      ]
    },
    {
      "case_number" : "10",
      "surgery_type" : "Intrathecal Baclofen Pump",
      "surgeon" : "Stephanie McGill MD, PhD",
      "date" : "2016-12-02T19:21:38.514Z",
      "items" : [
        {
          "item_name" : "Safety IV Catheters - Radiopaque (Jelco)",
          "donating": "0",
          "total": "1",
          "cost": "135.00"
        },
        {
          "item_name" : "Shiley Tracheostomy Tube Cuffless with Disposable Inner Cannula (Covidian)",
          "donating": "3",
          "total": "3",
          "cost": "75.21"
        },
        {
          "item_name" : "Dermacea USP Type VII Gauze (Covidien)",
          "donating": "0",
          "total": "10",
          "cost": "3.99"
        },
        {
          "item_name" : "0.9% Sodium Chloride Injection USP",
          "donating": "0",
          "total": "10",
          "cost": "10.95"
        },
        {
          "item_name" : "IV Secondary Set",
          "donating": "2",
          "total": "2",
          "cost": "5.00"
        }
      ]
    },
    {
      "case_number" : "11",
      "surgery_type" : "Spinal Fusion",
      "surgeon" : "Andrew Tran MD",
      "date" : "2016-12-02T21:31:38.514Z",
      "items" : [
        {
          "item_name" : "Safety IV Catheters - Radiopaque (Jelco)",
          "donating": "0",
          "total": "1",
          "cost": "135.00"
        },
        {
          "item_name" : "Shiley Tracheostomy Tube Cuffless with Disposable Inner Cannula (Covidian)",
          "donating": "0",
          "total": "3",
          "cost": "75.21"
        },
        {
          "item_name" : "Dermacea USP Type VII Gauze (Covidien)",
          "donating": "0",
          "total": "10",
          "cost": "3.99"
        },
        {
          "item_name" : "0.9% Sodium Chloride Injection USP",
          "donating": "0",
          "total": "10",
          "cost": "10.95"
        },
        {
          "item_name" : "IV Secondary Set",
          "donating": "0",
          "total": "2",
          "cost": "5.00"
        }
      ]
    },
    {
      "case_number" : "12",
      "surgery_type" : "Endoscopic Third Ventriculostomy (ETV)",
      "surgeon" : "Jonathan Bresenham MD",
      "date" : "2016-12-02T21:32:38.514Z",
      "items" : [
        {
          "item_name" : "Safety IV Catheters - Radiopaque (Jelco)",
          "donating": "0",
          "total": "1",
          "cost": "135.00"
        },
        {
          "item_name" : "Shiley Tracheostomy Tube Cuffless with Disposable Inner Cannula (Covidian)",
          "donating": "0",
          "total": "3",
          "cost": "75.21"
        },
        {
          "item_name" : "Dermacea USP Type VII Gauze (Covidien)",
          "donating": "0",
          "total": "10",
          "cost": "3.99"
        },
        {
          "item_name" : "0.9% Sodium Chloride Injection USP",
          "donating": "0",
          "total": "10",
          "cost": "10.95"
        },
        {
          "item_name" : "IV Secondary Set",
          "donating": "0",
          "total": "2",
          "cost": "5.00"
        }
      ]
    },
    {
      "case_number" : "13",
      "surgery_type" : "Spinal Fusion",
      "surgeon" : "Andrew Tran MD",
      "date" : "2016-12-01T22:33:38.514Z",
      "items" : [
        {
          "item_name" : "Safety IV Catheters - Radiopaque (Jelco)",
          "donating": "0",
          "total": "1",
          "cost": "135.00"
        },
        {
          "item_name" : "Swan-Ganz (Edwards Lifesciences)",
          "donating": "0",
          "total": "1",
          "cost": "1500.00"
        },
        {
          "item_name" : "Dermacea USP Type VII Gauze (Covidien)",
          "donating": "0",
          "total": "10",
          "cost": "3.99"
        },
        {
          "item_name" : "0.9% Sodium Chloride Injection USP",
          "donating": "0",
          "total": "10",
          "cost": "10.95"
        },
        {
          "item_name" : "IV Secondary Set",
          "donating": "0",
          "total": "2",
          "cost": "5.00"
        }
      ]
    },
    {
      "case_number" : "14",
      "surgery_type" : "External Venticular Drain (EVD)",
      "surgeon" : "Ethan Rutledge MD",
      "date" : "2016-12-02T19:38:38.514Z",
      "items" : [
        {
          "item_name" : "Safety IV Catheters - Radiopaque (Jelco)",
          "donating": "0",
          "total": "1",
          "cost": "135.00"
        },
        {
          "item_name" : "Shiley Tracheostomy Tube Cuffless with Disposable Inner Cannula (Covidian)",
          "donating": "0",
          "total": "3",
          "cost": "75.21"
        },
        {
          "item_name" : "Dermacea USP Type VII Gauze (Covidien)",
          "donating": "0",
          "total": "10",
          "cost": "3.99"
        },
        {
          "item_name" : "0.9% Sodium Chloride Injection USP",
          "donating": "0",
          "total": "10",
          "cost": "10.95"
        },
        {
          "item_name" : "IV Secondary Set",
          "donating": "0",
          "total": "2",
          "cost": "5.00"
        }
      ]
    },
    {
      "case_number" : "15",
      "surgery_type" : "Ventriculo-Peritoneal Shunt",
      "surgeon" : "Ethan Rutledge MD",
      "date" : "2016-12-01T22:39:38.514Z",
      "items" : [
        {
          "item_name" : "Safety IV Catheters - Radiopaque (Jelco)",
          "donating": "0",
          "total": "1",
          "cost": "135.00"
        },
        {
          "item_name" : "Shiley Tracheostomy Tube Cuffless with Disposable Inner Cannula (Covidian)",
          "donating": "0",
          "total": "3",
          "cost": "75.21"
        },
        {
          "item_name" : "Dermacea USP Type VII Gauze (Covidien)",
          "donating": "0",
          "total": "10",
          "cost": "3.99"
        },
        {
          "item_name" : "0.9% Sodium Chloride Injection USP",
          "donating": "0",
          "total": "10",
          "cost": "10.95"
        },
        {
          "item_name" : "IV Secondary Set",
          "donating": "0",
          "total": "2",
          "cost": "5.00"
        }
      ]
    },
    {
      "case_number" : "16",
      "surgery_type" : "Ventriculo-Peritoneal Shunt",
      "surgeon" : "Stephanie McGill MD, PhD",
      "date" : "2016-12-03T06:31:38.514Z",
      "items" : [
        {
          "item_name" : "Safety IV Catheters - Radiopaque (Jelco)",
          "donating": "0",
          "total": "1",
          "cost": "135.00"
        },
        {
          "item_name" : "Shiley Tracheostomy Tube Cuffless with Disposable Inner Cannula (Covidian)",
          "donating": "0",
          "total": "3",
          "cost": "75.21"
        },
        {
          "item_name" : "Dermacea USP Type VII Gauze (Covidien)",
          "donating": "0",
          "total": "10",
          "cost": "3.99"
        },
        {
          "item_name" : "0.9% Sodium Chloride Injection USP",
          "donating": "0",
          "total": "10",
          "cost": "10.95"
        },
        {
          "item_name" : "IV Secondary Set",
          "donating": "0",
          "total": "2",
          "cost": "5.00"
        }
      ]
    },
    {
      "case_number" : "17",
      "surgery_type" : "Ventriculo-Peritoneal Shunt",
      "surgeon" : "Daniel Lau MD",
      "date" : "2016-12-03T07:31:38.514Z",
      "items" : [
        {
          "item_name" : "Safety IV Catheters - Radiopaque (Jelco)",
          "donating": "0",
          "total": "1",
          "cost": "135.00"
        },
        {
          "item_name" : "Shiley Tracheostomy Tube Cuffless with Disposable Inner Cannula (Covidian)",
          "donating": "0",
          "total": "3",
          "cost": "75.21"
        },
        {
          "item_name" : "Swan-Ganz (Edwards Lifesciences)",
          "donating": "1",
          "total": "1",
          "cost": "1500.00"
        },
        {
          "item_name" : "0.9% Sodium Chloride Injection USP",
          "donating": "0",
          "total": "10",
          "cost": "10.95"
        },
        {
          "item_name" : "IV Secondary Set",
          "donating": "0",
          "total": "2",
          "cost": "5.00"
        }
      ]
    },
    {
      "case_number" : "18",
      "surgery_type" : "Craniectomy",
      "surgeon" : "Young Lam MD",
      "date" : "2016-12-01T08:20:38.514Z",
      "items" : [
        {
          "item_name" : "Safety IV Catheters - Radiopaque (Jelco)",
          "donating": "0",
          "total": "1",
          "cost": "135.00"
        },
        {
          "item_name" : "Shiley Tracheostomy Tube Cuffless with Disposable Inner Cannula (Covidian)",
          "donating": "0",
          "total": "3",
          "cost": "75.21"
        },
        {
          "item_name" : "Dermacea USP Type VII Gauze (Covidien)",
          "donating": "0",
          "total": "10",
          "cost": "3.99"
        },
        {
          "item_name" : "0.9% Sodium Chloride Injection USP",
          "donating": "0",
          "total": "10",
          "cost": "10.95"
        },
        {
          "item_name" : "IV Secondary Set",
          "donating": "0",
          "total": "2",
          "cost": "5.00"
        }
      ]
    }
  ]
}
